prlps_websearch/__init__.py
prlps_websearch/utils.py
prlps_websearch-0.0.7.dist-info/LICENSE.txt
prlps_websearch-0.0.7.dist-info/METADATA
prlps_websearch-0.0.7.dist-info/WHEEL
prlps_websearch-0.0.7.dist-info/top_level.txt
prlps_websearch-0.0.7.dist-info/RECORD
