Metadata-Version: 2.1
Name: prlps-websearch
Version: 0.0.7
Summary: веб поиск
Home-page: https://github.com/prolapser/prlps_websearch
Author: prolapser
License: LICENSE.txt
Classifier: Development Status :: 4 - Beta
Classifier: Intended Audience :: Developers
Classifier: License :: OSI Approved :: MIT License
Classifier: Operating System :: OS Independent
Requires-Python: >=3.10
License-File: LICENSE.txt
Requires-Dist: httpx
Requires-Dist: parsel
Requires-Dist: nest-asyncio
Requires-Dist: packaging
Requires-Dist: prlps-fakeua
